Metadata-Version: 2.1
Name: zyr-zhuanshu
Version: 0.0.1
Summary: zyr_zhuanshu
Home-page: https://github.com/jamwusjki/zyr_zhuanshu
Author: zyr_studio
Author-email: hexin991@qq.com
License: UNKNOWN
Platform: UNKNOWN
Classifier: Programming Language :: Python :: 3
Classifier: License :: OSI Approved :: MIT License
Classifier: Operating System :: OS Independent
License-File: LICENSE
